rifl/__init__.py
rifl/analysis.py
rifl/cli.py
rifl/config.py
rifl/dataset.py
rifl/exceptions.py
rifl/models.py
rifl/utils.py
rifl/version.py
rifl/filters/__init__.py
rifl/filters/isobaric.py
rifl/filters/isotopic.py
rifl/filters/shared.py
rifl/parse/__init__.py
rifl/parse/census.py
rifl/parse/cimage.py
rifl-0.0.1.dist-info/METADATA
rifl-0.0.1.dist-info/WHEEL
rifl-0.0.1.dist-info/entry_points.txt
rifl-0.0.1.dist-info/top_level.txt
rifl-0.0.1.dist-info/zip-safe
rifl-0.0.1.dist-info/RECORD
